gmxbatch/__init__.py
gmxbatch/indexgroups.py
gmxbatch/mdengine.py
gmxbatch/system.py
gmxbatch/templating.py
gmxbatch/trajectory.py
gmxbatch/xvgfile.py
gmxbatch/conffiles/__init__.py
gmxbatch/conffiles/conffile.py
gmxbatch/environment/__init__.py
gmxbatch/environment/barostat.py
gmxbatch/environment/environment.py
gmxbatch/environment/thermostat.py
gmxbatch/forcefields/__init__.py
gmxbatch/forcefields/amber.py
gmxbatch/forcefields/charmm.py
gmxbatch/forcefields/forcefield.py
gmxbatch/forcefields/gromos.py
gmxbatch/intermolecularinteractions/__init__.py
gmxbatch/intermolecularinteractions/interaction.py
gmxbatch/intermolecularinteractions/intermolecularinteractions.py
gmxbatch/mdp/__init__.py
gmxbatch/mdp/mdp.py
gmxbatch/mdp/sections.py
gmxbatch/moleculetype/__init__.py
gmxbatch/moleculetype/atom.py
gmxbatch/moleculetype/moleculetype.py
gmxbatch/simulation/__init__.py
gmxbatch/simulation/results.py
gmxbatch/simulation/simulation.py
gmxbatch/topfilter/__init__.py
gmxbatch/topfilter/topologyfilter.py
gmxbatch/utilities/__init__.py
gmxbatch/utilities/top2itp.py
gmxbatch-0.0.2.dev0.dist-info/LICENSE
gmxbatch-0.0.2.dev0.dist-info/METADATA
gmxbatch-0.0.2.dev0.dist-info/WHEEL
gmxbatch-0.0.2.dev0.dist-info/entry_points.txt
gmxbatch-0.0.2.dev0.dist-info/top_level.txt
gmxbatch-0.0.2.dev0.dist-info/RECORD
