Metadata-Version: 2.1
Name: gmxbatch
Version: 0.0.2.dev0
Summary: Python tools for writing GROMACS batch scripts
Home-page: http://gitlab.com/awacha/gmxbatch
Author: Andras Wacha
Author-email: awacha@gmail.com
License: BSD-3-Clause
Keywords: GROMACS batch GMX scripting molecular dynamics
Platform: UNKNOWN
Classifier: Environment :: Console
Classifier: Development Status :: 3 - Alpha
Classifier: Intended Audience :: Science/Research
Classifier: Intended Audience :: Education
Classifier: License :: OSI Approved :: BSD License
Classifier: Operating System :: POSIX
Classifier: Programming Language :: Python :: 3 :: Only
Classifier: Topic :: Scientific/Engineering :: Bio-Informatics
Classifier: Topic :: Scientific/Engineering :: Chemistry
Classifier: Topic :: Scientific/Engineering :: Physics
Requires-Dist: setuptools-scm
Requires-Dist: jinja2
Requires-Dist: numpy (>=1.15.0)
Requires-Dist: matplotlib (>=3.0.0)
